old/regfile.v
`include "regfile.h"

module regfile(
	input wire clk,
	input wire reset,
	input wire [`ADDRBUS] addr,
	input wire [`DATABUS] d_in,
	input wire we,
	output wire [`DATABUS] d_out
);

reg [`DATABUS] reg_file[`DATA_D-1:0];
integer i;

assign d_out = reg_file[addr];

always @(posedge clk or negedge reset) 
begin
	if(reset == `ENABLE)
	begin
		for(i = 0; i < `DATA_D; i=i+1)
		begin
			reg_file[i] <= {`DATA_W{1'b0}}; 
		end
	end
	else 
	begin
		if(we == `ENABLE)
		begin
			reg_file[addr] <= d_in;
		end
	end
end

endmodule // regfile

old/regfile_test.v
`timescale 1ns/1ps
`include "regfile.h"

module regfile_test ;
	reg clk;
	reg reset;
	reg [`ADDRBUS] addr;
	reg [`DATABUS] d_in;
	reg we;
	wire [`DATABUS] d_out;
	integer i;
	parameter STEP = 100.000;

always #(STEP/2)
begin
	clk <= ~clk;
end

regfile regfile(
	.clk(clk),
	.reset(reset),
	.addr(addr),
	.d_in(d_in),
	.we(we),
	.d_out(d_out)
);

initial
begin
	# 0
	begin
		clk <= 0;
		reset <= `ENABLE;
		addr <= {`ADDR_W{1'b0}};
		d_in <= {`DATA_W{1'b0}};
		we <= `DISABLE;
	end

	#STEP
	begin
		reset <= `DISABLE;
	end

	#STEP
	begin
		for(i = 0; i < `DATA_D; i = i+1)
		begin
			#STEP
			begin
				addr <= i;
				d_in <= i;
				we <= `ENABLE;
			end
			#STEP
			begin
				addr <= {`ADDR_W{1'b0}};
				d_in <= {`DATA_W{1'b0}};
				we <= `DISABLE;
				if(d_out == i)
				begin
					$display($time," regfile[%d] R/W Check OK! %d", i, d_out);
				end
				else
				begin
					$display($time," regfile[%d] R/W Check NG! %d", i, d_out);
				end
			end

		end
	end
	#STEP
	begin
		$finish;
	end
end

initial
begin
	$dumpfile("regfile.vcd");
	$dumpvars(0, regfile);
end

endmodule

old/regfile.vcd
$date
	Thu Oct 26 19:53:14 2017
$end
$version
	Icarus Verilog
$end
$timescale
	1ps
$end
$scope module regfile_test $end
$scope module regfile $end
$var wire 5 ! addr [4:0] $end
$var wire 1 " clk $end
$var wire 32 # d_in [31:0] $end
$var wire 32 $ d_out [31:0] $end
$var wire 1 % reset $end
$var wire 1 & we $end
$var integer 32 ' i [31:0] $end
$upscope $end
$upscope $end
$enddefinitions $end
#0
$dumpvars
b100000 '
1&
0%
b0 $
b0 #
0"
b0 !
$end
#50000
b100000 '
1"
#100000
0"
1%
#150000
1"
#200000
0"
#250000
1"
#300000
0"
0&
#350000
1"
#400000
0"
1&
#450000
1"
#500000
0"
0&
b1 #
b1 !
#550000
b1 $
1"
#600000
0"
1&
b0 #
b0 $
b0 !
#650000
1"
#700000
0"
0&
b10 #
b10 !
#750000
b10 $
1"
#800000
0"
1&
b0 #
b0 $
b0 !
#850000
1"
#900000
0"
0&
b11 #
b11 !
#950000
b11 $
1"
#1000000
0"
1&
b0 #
b0 $
b0 !
#1050000
1"
#1100000
0"
0&
b100 #
b100 !
#1150000
b100 $
1"
#1200000
0"
1&
b0 #
b0 $
b0 !
#1250000
1"
#1300000
0"
0&
b101 #
b101 !
#1350000
b101 $
1"
#1400000
0"
1&
b0 #
b0 $
b0 !
#1450000
1"
#1500000
0"
0&
b110 #
b110 !
#1550000
b110 $
1"
#1600000
0"
1&
b0 #
b0 $
b0 !
#1650000
1"
#1700000
0"
0&
b111 #
b111 !
#1750000
b111 $
1"
#1800000
0"
1&
b0 #
b0 $
b0 !
#1850000
1"
#1900000
0"
0&
b1000 #
b1000 !
#1950000
b1000 $
1"
#2000000
0"
1&
b0 #
b0 $
b0 !
#2050000
1"
#2100000
0"
0&
b1001 #
b1001 !
#2150000
b1001 $
1"
#2200000
0"
1&
b0 #
b0 $
b0 !
#2250000
1"
#2300000
0"
0&
b1010 #
b1010 !
#2350000
b1010 $
1"
#2400000
0"
1&
b0 #
b0 $
b0 !
#2450000
1"
#2500000
0"
0&
b1011 #
b1011 !
#2550000
b1011 $
1"
#2600000
0"
1&
b0 #
b0 $
b0 !
#2650000
1"
#2700000
0"
0&
b1100 #
b1100 !
#2750000
b1100 $
1"
#2800000
0"
1&
b0 #
b0 $
b0 !
#2850000
1"
#2900000
0"
0&
b1101 #
b1101 !
#2950000
b1101 $
1"
#3000000
0"
1&
b0 #
b0 $
b0 !
#3050000
1"
#3100000
0"
0&
b1110 #
b1110 !
#3150000
b1110 $
1"
#3200000
0"
1&
b0 #
b0 $
b0 !
#3250000
1"
#3300000
0"
0&
b1111 #
b1111 !
#3350000
b1111 $
1"
#3400000
0"
1&
b0 #
b0 $
b0 !
#3450000
1"
#3500000
0"
0&
b10000 #
b10000 !
#3550000
b10000 $
1"
#3600000
0"
1&
b0 #
b0 $
b0 !
#3650000
1"
#3700000
0"
0&
b10001 #
b10001 !
#3750000
b10001 $
1"
#3800000
0"
1&
b0 #
b0 $
b0 !
#3850000
1"
#3900000
0"
0&
b10010 #
b10010 !
#3950000
b10010 $
1"
#4000000
0"
1&
b0 #
b0 $
b0 !
#4050000
1"
#4100000
0"
0&
b10011 #
b10011 !
#4150000
b10011 $
1"
#4200000
0"
1&
b0 #
b0 $
b0 !
#4250000
1"
#4300000
0"
0&
b10100 #
b10100 !
#4350000
b10100 $
1"
#4400000
0"
1&
b0 #
b0 $
b0 !
#4450000
1"
#4500000
0"
0&
b10101 #
b10101 !
#4550000
b10101 $
1"
#4600000
0"
1&
b0 #
b0 $
b0 !
#4650000
1"
#4700000
0"
0&
b10110 #
b10110 !
#4750000
b10110 $
1"
#4800000
0"
1&
b0 #
b0 $
b0 !
#4850000
1"
#4900000
0"
0&
b10111 #
b10111 !
#4950000
b10111 $
1"
#5000000
0"
1&
b0 #
b0 $
b0 !
#5050000
1"
#5100000
0"
0&
b11000 #
b11000 !
#5150000
b11000 $
1"
#5200000
0"
1&
b0 #
b0 $
b0 !
#5250000
1"
#5300000
0"
0&
b11001 #
b11001 !
#5350000
b11001 $
1"
#5400000
0"
1&
b0 #
b0 $
b0 !
#5450000
1"
#5500000
0"
0&
b11010 #
b11010 !
#5550000
b11010 $
1"
#5600000
0"
1&
b0 #
b0 $
b0 !
#5650000
1"
#5700000
0"
0&
b11011 #
b11011 !
#5750000
b11011 $
1"
#5800000
0"
1&
b0 #
b0 $
b0 !
#5850000
1"
#5900000
0"
0&
b11100 #
b11100 !
#5950000
b11100 $
1"
#6000000
0"
1&
b0 #
b0 $
b0 !
#6050000
1"
#6100000
0"
0&
b11101 #
b11101 !
#6150000
b11101 $
1"
#6200000
0"
1&
b0 #
b0 $
b0 !
#6250000
1"
#6300000
0"
0&
b11110 #
b11110 !
#6350000
b11110 $
1"
#6400000
0"
1&
b0 #
b0 $
b0 !
#6450000
1"
#6500000
0"
0&
b11111 #
b11111 !
#6550000
b11111 $
1"
#6600000
0"
1&
b0 #
b0 $
b0 !
